sbt_aws_cli/__init__.py
sbt_aws_cli/main.py
sbt_aws_cli-0.0.1.dist-info/METADATA
sbt_aws_cli-0.0.1.dist-info/WHEEL
sbt_aws_cli-0.0.1.dist-info/entry_points.txt
sbt_aws_cli-0.0.1.dist-info/RECORD
