Metadata-Version: 2.1
Name: sbt-aws-cli
Version: 0.0.1
Summary: 
Author: sbt-aws
Author-email: sbt-aws-maintainers@amazon.com
Requires-Python: >=3.12,<4.0
Classifier: Programming Language :: Python :: 3
Classifier: Programming Language :: Python :: 3.12
Requires-Dist: requests (>=2.32.3,<3.0.0)
Requires-Dist: typer (>=0.12.5,<0.13.0)
